Workbook

Sheet MuleIntegrations<=>MuleApps
A1: Sr No | B1: MuleSoft Integrations | C1: MuleSoft Applications | D1: Medium | E1: Comments
A2: 1 | B2: MUL-CONSOLIDATEDINVOICE | C2: columbus-document-papi-v1 | D2: Mixed
A3: 2 | B3: MUL-CONSOLIDATEDINVOICE | C3: columbus-document-sapi-v1 | D3: Mixed
A4: 3 | B4: MUL-CONSOLIDATEDINVOICE | C4: customer-document-papi-v1 | D4: Mixed
A5: 4 | B5: MUL-CONSOLIDATEDINVOICE | C5: hx-sftp-sapi-v1 | D5: Mixed
A6: 5 | B6: MUL-CONSOLIDATEDINVOICE | C6: invoice-papi-v1 | D6: Mixed
A7: 6 | B7: MUL-CONSOLIDATEDINVOICE | C7: sfdc-order-sapi-v1 | D7: Mixed
A8: 7 | B8: MUL-CONSOLIDATEDINVOICE | C8: sfdc-product-sapi-v1 | D8: Mixed
A9: 8 | B9: MUL-CONSOLIDATEDINVOICE | C9: vanstock-invoice-sapi-v1 | D9: Mixed
A10: 9 | B10: MUL-DIGITALASSET | C10: azure-blob-storage-sapi-v1 | D10: API
A11: 10 | B11: MUL-DIGITALASSET | C11: digitalasset-papi-v1 | D11: API
A12: 11 | B12: MUL-DIGITALASSET | C12: cloudinary-digitalasset-sapi-live | D12: API
A13: 12 | B13: MUL-COLUMBUS-DOC-HYBRIS | C13: api-hybrisdocuments-v2 | D13: API
... A16: 15 | B16: MUL-COLUMBUS-DOC-HYBRIS | C16: mule-oauth-provider | D16: API
A17: 16 | B17: MUL-COLUMBUSFILES | C17: columbus-document-papi-v1 | D17: File Transfer | E17: FelixToAzureStarkAndColumbus UAT Pending
A18: 17 | B18: MUL-COLUMBUSFILES | C18: columbus-document-sapi-v1 | D18: File Transfer | E18: HxToAzureStarkAndColumbus UAT pending
A19: 18 | B19: MUL-COLUMBUSFILES | C19: icon-sftp-sapi-v1 | D19: File Transfer
A20: 19 | B20: MUL-COLUMBUSFILES | C20: felix-sftp-sapi-v1 | D20: File Transfer | E20: FelixToAzureStarkAndColumbus UAT Pending
A21: 20 | B21: MUL-COLUMBUSFILES | C21: hx-sftp-sapi-v1 | D21: File Transfer | E21: HxToAzureStarkAndColumbus UAT pending
A22: 21 | B22: MUL-COLUMBUS-DOCUMENTS | C22: document-eapi-v2 | D22: API
A23: 22 | B23: MUL-COLUMBUS-DOCUMENTS | C23: document-papi-v1 | D23: API
A24: 23 | B24: MUL-COLUMBUS-DOCUMENTS | C24: columbus-document-sapi-v1 | D24: API
A25: 24 | B25: MUL-COLUMBUS-DOCUMENTS | C25: mule-oauth-provider | D25: API
A26: 25 | B26: MUL-ACCOUNT-VALIDATION | C26: account-validation-eapi-v1 | D26: Mixed
A27: 26 | B27: MUL-ACCOUNT-VALIDATION | C27: account-validation-papi-v1 | D27: Mixed
A28: 27 | B28: MUL-ACCOUNT-VALIDATION | C28: icon-account-sapi-v1 | D28: Mixed
A29: 28 | B29: MUL-ACCOUNT-VALIDATION | C29: dbm-sapi-v1 | D29: Mixed
A30: 29 | B30: MUL-ACCOUNT-VALIDATION | C30: pmsolutions-sapi-v1 | D30: Mixed
A31: 30 | B31: MUL-ACCOUNT-VALIDATION | C31: mule-oauth-provider | D31: Mixed
A32: 31 | B32: MUL-TIMBERDATABASE | C32: timber-papi-v1 | D32: File Transfer | E32: UAT pending
A33: 32 | B33: MUL-TIMBERDATABASE | C33: felix-sftp-sapi-v1 | D33: File Transfer | E33: UAT pending
A34: 33 | B34: MUL-TIMBERDATABASE | C34: azure-file-sapi-v1 | D34: File Transfer | E34: UAT pending
A35: 34 | B35: MUL-FLEETWAVE-ICON-COGNITO | C35: transport-papi-v1 | D35: Mixed | E35: UAT pending
A36: 35 | B36: MUL-FLEETWAVE-ICON-COGNITO | C36: fleetwave-sapi-v1 | D36: Mixed | E36: UAT pending
A37: 36 | B37: MUL-FLEETWAVE-ICON-COGNITO | C37: icon-sftp-sapi-v1 | D37: Mixed | E37: UAT pending
A38: 37 | B38: MUL-FLEETWAVE-ICON-COGNITO | C38: cognito-sapi-v1 | D38: Mixed | E38: UAT pending
A39: 38 | B39: MUL-TRIPDATA | C39: rac-sapi-v1 | D39: API | E39: Out of Scope
A40: 39 | B40: MUL-TRIPDATA | C40: fleetwave-sapi-v1 | D40: API | E40: Out of Scope
A41: 40 | B41: MUL-SWIFT6-TRANSPORT | C41: transport-papi-v1 | D41: Mixed | E41: Out of Scope
A42: 41 | B42: MUL-SWIFT6-TRANSPORT | C42: fleetwave-sapi-v1 | D42: Mixed | E42: Out of Scope
A43: 42 | B43: MUL-SWIFT6-TRANSPORT | C43: swift6-sapi-v1 | D43: Mixed | E43: Out of Scope
... A46: 45 | B46: MUL-ICERTIS | C46: phocas-cloud-sapi-v1 | D46: File Transfer | E46: Out of Scope
A47: 46 | B47: MUL-ERP-3rd-PARTY | C47: bi-papi-v2 | D47: File Transfer
A48: 47 | B48: MUL-ERP-3rd-PARTY | C48: dbm-sapi-v1 | D48: File Transfer | E48: Out of Scope
A49: 48 | B49: MUL-ERP-3rd-PARTY | C49: insight-sapi-v1 | D49: File Transfer
A50: 49 | B50: MUL-ERP-3rd-PARTY | C50: hx-sftp-sapi-v1 | D50: File Transfer
A51: 50 | B51: MUL-ERP-3rd-PARTY | C51: felix-sftp-sapi-v1 | D51: File Transfer
A52: 51 | B52: MUL-ERP-3rd-PARTY | C52: icon-sftp-sapi-v1 | D52: File Transfer
A53: 52 | B53: MUL-TRUECOMMERCE | C53: edi-papi-v1 | D53: File Transfer | E53: Truecommerce to HX - UAT pending after Prod issue
A54: 53 | B54: MUL-TRUECOMMERCE | C54: icon-sftp-sapi-v1 | D54: File Transfer
A55: 54 | B55: MUL-TRUECOMMERCE | C55: hx-sftp-sapi-v1 | D55: File Transfer | E55: Truecommerce to HX - UAT pending after Prod issue
A56: 55 | B56: MUL-TRUECOMMERCE | C56: felix-sftp-sapi-v1 | D56: File Transfer
A57: 56 | B57: MUL-TRUECOMMERCE | C57: tradex-sftp-sapi-v1 | D57: File Transfer
A58: 57 | B58: MUL-TRUECOMMERCE | C58: truecommerce-sapi-v1 | D58: File Transfer | E58: Truecommerce to HX - UAT pending after Prod issue
A59: 58 | B59: MUL-PHOCAS-CREDITCONTROL | C59: phocas-cloud-papi-v1 | D59: File Transfer
A60: 59 | B60: MUL-PHOCAS-CREDITCONTROL | C60: hx-sftp-sapi-v1 | D60: File Transfer
A61: 60 | B61: MUL-PHOCAS-CREDITCONTROL | C61: icon-sftp-sapi-v1 | D61: File Transfer
A62: 61 | B62: MUL-PHOCAS-CREDITCONTROL | C62: phocas-cloud-sapi-v1 | D62: File Transfer
A63: 62 | B63: MUL-PHOCAS-DAILYDATA | C63: phocas-cloud-papi-v1 | D63: File Transfer
A64: 63 | B64: MUL-PHOCAS-DAILYDATA | C64: hx-sftp-sapi-v1 | D64: File Transfer
A65: 64 | B65: MUL-PHOCAS-DAILYDATA | C65: icon-sftp-sapi-v1 | D65: File Transfer
A66: 65 | B66: MUL-PHOCAS-DAILYDATA | C66: phocas-cloud-sapi-v1 | D66: File Transfer
A67: 66 | B67: MUL-ICONACCOUNTS | C67: account-eapi-v2 | D67: API
A68: 67 | B68: MUL-ICONACCOUNTS | C68: icon-account-sapi-v1 | D68: API
A69: 68 | B69: MUL-ICONACCOUNTS | C69: mule-oauth-provider | D69: API
A70: 69 | B70: MUL-DATALAKE | C70: bi-papi-v1 | D70: File Transfer
... A73: 72 | B73: MUL-DATALAKE | C73: hx-sftp-sapi-v1 | D73: File Transfer
A74: 73 | B74: MUL-DATALAKE | C74: sfdc-invoice-etl-papi-v1 | D74: File Transfer | E74: This is being covered under MUL-CONSXREF
A75: 74 | B75: MUL-PRODUCT-FEED | C75: product-feed-papi-v1 | D75: Mixed
A76: 75 | B76: MUL-PRODUCT-FEED | C76: azure-blob-storage-sapi-v1 | D76: Mixed
A77: 76 | B77: MUL-PRODUCT-FEED | C77: bloomreach-sapi-v1 | D77: Mixed
A78: 77 | B78: MUL-PRODUCT-FEED | C78: gmc-sapi-v1 | D78: Mixed
A79: 78 | B79: MUL-PRODUCT-FEED | C79: rakuten-sapi-v1 | D79: Mixed
A80: 79 | B80: MUL-PRODUCT-FEED | C80: stibo-sapi-v1 | D80: Mixed
A81: 80 | B81: MUL-PRODUCT-FEED | C81: outbound-proxy-sapi-v1 | D81: Mixed
A82: 81 | B82: MUL-BACS-FILES | C82: bacs-papi-v1 | D82: File Transfer
A83: 82 | B83: MUL-BACS-FILES | C83: icon-sftp-sapi-v1 | D83: File Transfer
A84: 83 | B84: MUL-BACS-FILES | C84: hx-sftp-sapi-v1 | D84: File Transfer
A85: 84 | B85: MUL-BACS-FILES | C85: felix-sftp-sapi-v1 | D85: File Transfer
A86: 85 | B86: MUL-BACS-FILES | C86: azure-blob-storage-sapi-v1 | D86: File Transfer
A87: 86 | B87: MUL-BRINGG | C87: order-delivery-papi-v1 | D87: API | E87: Out of Scope
A88: 87 | B88: MUL-BRINGG | C88: bringg-order-sapi-v1 | D88: API | E88: Out of Scope
A89: 88 | B89: MUL-BRINGG | C89: icon-order-sapi-v3 | D89: API | E89: Out of Scope
A90: 89 | B90: MUL-SUPPLIER-OCR | C90: cognizant-sftp-sapi-v1 | D90: File Transfer | E90: Out of Scope
A91: 90 | B91: MUL-SUPPLIER-OCR | C91: supplier-invoice-papi-v1 | D91: File Transfer | E91: Out of Scope
A92: 91 | B92: MUL-SUPPLIER-OCR | C92: icon-sftp-sapi-v1 | D92: File Transfer | E92: Out of Scope
A93: 92 | B93: MUL-SUPPLIER-OCR | C93: columbus-document-sapi-v1 | D93: File Transfer | E93: Out of Scope
A94: 93 | B94: MUL-EXPERIAN | C94: icon-sftp-sapi-v1 | D94: File Transfer | E94: Out of Scope
A95: 94 | B95: MUL-EXPERIAN | C95: experian-papi-v1 | D95: File Transfer | E95: Out of Scope
A96: 95 | B96: MUL-EXPERIAN | C96: experian-sapi-v1 | D96: File Transfer | E96: Out of Scope
A97: 96 | B97: MUL-ICON-TIMBER-PO | C97: timber-papi-v1 | D97: File Transfer
A98: 97 | B98: MUL-ICON-TIMBER-PO | C98: icon-sftp-sapi-v1 | D98: File Transfer
A99: 98 | B99: MUL-ICON-TIMBER-PO | C99: felix-sftp-sapi-v1 | D99: File Transfer
A100: 99 | B100: MUL-SWISSPOST | C100: customer-document-papi-v1 | D100: File Transfer
A101: 100 | B101: MUL-SWISSPOST | C101: icon-sftp-sapi-v1 | D101: File Transfer
A102: 101 | B102: MUL-SWISSPOST | C102: felix-sftp-sapi-v1 | D102: File Transfer
A103: 102 | B103: MUL-SWISSPOST | C103: hx-sftp-sapi-v1 | D103: File Transfer
A104: 103 | B104: MUL-SWISSPOST | C104: swisspost-sapi-v1 | D104: File Transfer
A105: 104 | B105: MUL-SWISSPOST | C105: columbus-document-sapi-v1 | D105: File Transfer
A106: 105 | B106: MUL-TIMBERSUPPLIERS | C106: timber-papi-v1 | D106: Mixed | E106: UAT pending
...

Sheet MuleApps<=>MuleIntegrations
A1: Sr No | B1: MuleSoft Applications | C1: MuleSoft Integrations | D1: Medium | E1: Comments
A2: 1 | B2: columbus-document-papi-v1 | C2: MUL-CONSOLIDATEDINVOICE | D2: Mixed
A3: 2 | B3: columbus-document-sapi-v1 | C3: MUL-CONSOLIDATEDINVOICE | D3: Mixed
A4: 3 | B4: customer-document-papi-v1 | C4: MUL-CONSOLIDATEDINVOICE | D4: Mixed
A5: 4 | B5: hx-sftp-sapi-v1 | C5: MUL-CONSOLIDATEDINVOICE | D5: Mixed
A6: 5 | B6: invoice-papi-v1 | C6: MUL-CONSOLIDATEDINVOICE | D6: Mixed
A7: 6 | B7: sfdc-order-sapi-v1 | C7: MUL-CONSOLIDATEDINVOICE | D7: Mixed
A8: 7 | B8: sfdc-product-sapi-v1 | C8: MUL-CONSOLIDATEDINVOICE | D8: Mixed
A9: 8 | B9: vanstock-invoice-sapi-v1 | C9: MUL-CONSOLIDATEDINVOICE | D9: Mixed
A10: 9 | B10: azure-blob-storage-sapi-v1 | C10: MUL-DIGITALASSET | D10: API
A11: 10 | B11: digitalasset-papi-v1 | C11: MUL-DIGITALASSET | D11: API
A12: 11 | B12: cloudinary-digitalasset-sapi-live | C12: MUL-DIGITALASSET | D12: API
A13: 12 | B13: api-hybrisdocuments-v2 | C13: MUL-COLUMBUS-DOC-HYBRIS | D13: API
... A16: 15 | B16: mule-oauth-provider | C16: MUL-COLUMBUS-DOC-HYBRIS | D16: API
A17: 16 | B17: columbus-document-papi-v1 | C17: MUL-COLUMBUSFILES | D17: File Transfer | E17: FelixToAzureStarkAndColumbus UAT Pending
A18: 17 | B18: columbus-document-sapi-v1 | C18: MUL-COLUMBUSFILES | D18: File Transfer | E18: HxToAzureStarkAndColumbus UAT pending
A19: 18 | B19: icon-sftp-sapi-v1 | C19: MUL-COLUMBUSFILES | D19: File Transfer
A20: 19 | B20: felix-sftp-sapi-v1 | C20: MUL-COLUMBUSFILES | D20: File Transfer | E20: FelixToAzureStarkAndColumbus UAT Pending
A21: 20 | B21: hx-sftp-sapi-v1 | C21: MUL-COLUMBUSFILES | D21: File Transfer | E21: HxToAzureStarkAndColumbus UAT pending
A22: 21 | B22: document-eapi-v2 | C22: MUL-COLUMBUS-DOCUMENTS | D22: API
A23: 22 | B23: document-papi-v1 | C23: MUL-COLUMBUS-DOCUMENTS | D23: API
A24: 23 | B24: columbus-document-sapi-v1 | C24: MUL-COLUMBUS-DOCUMENTS | D24: API
A25: 24 | B25: mule-oauth-provider | C25: MUL-COLUMBUS-DOCUMENTS | D25: API
A26: 25 | B26: account-validation-eapi-v1 | C26: MUL-ACCOUNT-VALIDATION | D26: Mixed
A27: 26 | B27: account-validation-papi-v1 | C27: MUL-ACCOUNT-VALIDATION | D27: Mixed
A28: 27 | B28: icon-account-sapi-v1 | C28: MUL-ACCOUNT-VALIDATION | D28: Mixed
A29: 28 | B29: dbm-sapi-v1 | C29: MUL-ACCOUNT-VALIDATION | D29: Mixed
A30: 29 | B30: pmsolutions-sapi-v1 | C30: MUL-ACCOUNT-VALIDATION | D30: Mixed
A31: 30 | B31: mule-oauth-provider | C31: MUL-ACCOUNT-VALIDATION | D31: Mixed
A32: 31 | B32: timber-papi-v1 | C32: MUL-TIMBERDATABASE | D32: File Transfer | E32: UAT pending
A33: 32 | B33: felix-sftp-sapi-v1 | C33: MUL-TIMBERDATABASE | D33: File Transfer | E33: UAT pending
A34: 33 | B34: azure-file-sapi-v1 | C34: MUL-TIMBERDATABASE | D34: File Transfer | E34: UAT pending
A35: 34 | B35: transport-papi-v1 | C35: MUL-FLEETWAVE-ICON-COGNITO | D35: Mixed | E35: UAT pending
A36: 35 | B36: fleetwave-sapi-v1 | C36: MUL-FLEETWAVE-ICON-COGNITO | D36: Mixed | E36: UAT pending
A37: 36 | B37: icon-sftp-sapi-v1 | C37: MUL-FLEETWAVE-ICON-COGNITO | D37: Mixed | E37: UAT pending
A38: 37 | B38: cognito-sapi-v1 | C38: MUL-FLEETWAVE-ICON-COGNITO | D38: Mixed | E38: UAT pending
A39: 38 | B39: rac-sapi-v1 | C39: MUL-TRIPDATA | D39: API | E39: Out of Scope
A40: 39 | B40: fleetwave-sapi-v1 | C40: MUL-TRIPDATA | D40: API | E40: Out of Scope
A41: 40 | B41: transport-papi-v1 | C41: MUL-SWIFT6-TRANSPORT | D41: Mixed | E41: Out of Scope
A42: 41 | B42: fleetwave-sapi-v1 | C42: MUL-SWIFT6-TRANSPORT | D42: Mixed | E42: Out of Scope
A43: 42 | B43: swift6-sapi-v1 | C43: MUL-SWIFT6-TRANSPORT | D43: Mixed | E43: Out of Scope
... A46: 45 | B46: phocas-cloud-sapi-v1 | C46: MUL-ICERTIS | D46: File Transfer | E46: Out of Scope
A47: 46 | B47: bi-papi-v2 | C47: MUL-ERP-3rd-PARTY | D47: File Transfer
A48: 47 | B48: dbm-sapi-v1 | C48: MUL-ERP-3rd-PARTY | D48: File Transfer | E48: Out of Scope
A49: 48 | B49: insight-sapi-v1 | C49: MUL-ERP-3rd-PARTY | D49: File Transfer
A50: 49 | B50: hx-sftp-sapi-v1 | C50: MUL-ERP-3rd-PARTY | D50: File Transfer
A51: 50 | B51: felix-sftp-sapi-v1 | C51: MUL-ERP-3rd-PARTY | D51: File Transfer
A52: 51 | B52: icon-sftp-sapi-v1 | C52: MUL-ERP-3rd-PARTY | D52: File Transfer
A53: 52 | B53: edi-papi-v1 | C53: MUL-TRUECOMMERCE | D53: File Transfer | E53: Truecommerce to HX - UAT pending after Prod issue
A54: 53 | B54: icon-sftp-sapi-v1 | C54: MUL-TRUECOMMERCE | D54: File Transfer
A55: 54 | B55: hx-sftp-sapi-v1 | C55: MUL-TRUECOMMERCE | D55: File Transfer | E55: Truecommerce to HX - UAT pending after Prod issue
A56: 55 | B56: felix-sftp-sapi-v1 | C56: MUL-TRUECOMMERCE | D56: File Transfer
A57: 56 | B57: tradex-sftp-sapi-v1 | C57: MUL-TRUECOMMERCE | D57: File Transfer
A58: 57 | B58: truecommerce-sapi-v1 | C58: MUL-TRUECOMMERCE | D58: File Transfer | E58: Truecommerce to HX - UAT pending after Prod issue
A59: 58 | B59: phocas-cloud-papi-v1 | C59: MUL-PHOCAS-CREDITCONTROL | D59: File Transfer
A60: 59 | B60: hx-sftp-sapi-v1 | C60: MUL-PHOCAS-CREDITCONTROL | D60: File Transfer
A61: 60 | B61: icon-sftp-sapi-v1 | C61: MUL-PHOCAS-CREDITCONTROL | D61: File Transfer
A62: 61 | B62: phocas-cloud-sapi-v1 | C62: MUL-PHOCAS-CREDITCONTROL | D62: File Transfer
A63: 62 | B63: phocas-cloud-papi-v1 | C63: MUL-PHOCAS-DAILYDATA | D63: File Transfer
A64: 63 | B64: hx-sftp-sapi-v1 | C64: MUL-PHOCAS-DAILYDATA | D64: File Transfer
A65: 64 | B65: icon-sftp-sapi-v1 | C65: MUL-PHOCAS-DAILYDATA | D65: File Transfer
A66: 65 | B66: phocas-cloud-sapi-v1 | C66: MUL-PHOCAS-DAILYDATA | D66: File Transfer
A67: 66 | B67: account-eapi-v2 | C67: MUL-ICONACCOUNTS | D67: API
A68: 67 | B68: icon-account-sapi-v1 | C68: MUL-ICONACCOUNTS | D68: API
A69: 68 | B69: mule-oauth-provider | C69: MUL-ICONACCOUNTS | D69: API
A70: 69 | B70: bi-papi-v1 | C70: MUL-DATALAKE | D70: File Transfer
... A73: 72 | B73: hx-sftp-sapi-v1 | C73: MUL-DATALAKE | D73: File Transfer
A74: 73 | B74: sfdc-invoice-etl-papi-v1 | C74: MUL-DATALAKE | D74: File Transfer | E74: This is being covered under MUL-CONSXREF
A75: 74 | B75: product-feed-papi-v1 | C75: MUL-PRODUCT-FEED | D75: Mixed
A76: 75 | B76: azure-blob-storage-sapi-v1 | C76: MUL-PRODUCT-FEED | D76: Mixed
A77: 76 | B77: bloomreach-sapi-v1 | C77: MUL-PRODUCT-FEED | D77: Mixed
A78: 77 | B78: gmc-sapi-v1 | C78: MUL-PRODUCT-FEED | D78: Mixed
A79: 78 | B79: rakuten-sapi-v1 | C79: MUL-PRODUCT-FEED | D79: Mixed
A80: 79 | B80: stibo-sapi-v1 | C80: MUL-PRODUCT-FEED | D80: Mixed
A81: 80 | B81: outbound-proxy-sapi-v1 | C81: MUL-PRODUCT-FEED | D81: Mixed
A82: 81 | B82: bacs-papi-v1 | C82: MUL-BACS-FILES | D82: File Transfer
A83: 82 | B83: icon-sftp-sapi-v1 | C83: MUL-BACS-FILES | D83: File Transfer
A84: 83 | B84: hx-sftp-sapi-v1 | C84: MUL-BACS-FILES | D84: File Transfer
A85: 84 | B85: felix-sftp-sapi-v1 | C85: MUL-BACS-FILES | D85: File Transfer
A86: 85 | B86: azure-blob-storage-sapi-v1 | C86: MUL-BACS-FILES | D86: File Transfer
A87: 86 | B87: order-delivery-papi-v1 | C87: MUL-BRINGG | D87: API | E87: Out of Scope
A88: 87 | B88: bringg-order-sapi-v1 | C88: MUL-BRINGG | D88: API | E88: Out of Scope
A89: 88 | B89: icon-order-sapi-v3 | C89: MUL-BRINGG | D89: API | E89: Out of Scope
A90: 89 | B90: cognizant-sftp-sapi-v1 | C90: MUL-SUPPLIER-OCR | D90: File Transfer | E90: Out of Scope
A91: 90 | B91: supplier-invoice-papi-v1 | C91: MUL-SUPPLIER-OCR | D91: File Transfer | E91: Out of Scope
A92: 91 | B92: icon-sftp-sapi-v1 | C92: MUL-SUPPLIER-OCR | D92: File Transfer | E92: Out of Scope
A93: 92 | B93: columbus-document-sapi-v1 | C93: MUL-SUPPLIER-OCR | D93: File Transfer | E93: Out of Scope
A94: 93 | B94: icon-sftp-sapi-v1 | C94: MUL-EXPERIAN | D94: File Transfer | E94: Out of Scope
A95: 94 | B95: experian-papi-v1 | C95: MUL-EXPERIAN | D95: File Transfer | E95: Out of Scope
A96: 95 | B96: experian-sapi-v1 | C96: MUL-EXPERIAN | D96: File Transfer | E96: Out of Scope
A97: 96 | B97: timber-papi-v1 | C97: MUL-ICON-TIMBER-PO | D97: File Transfer
A98: 97 | B98: icon-sftp-sapi-v1 | C98: MUL-ICON-TIMBER-PO | D98: File Transfer
A99: 98 | B99: felix-sftp-sapi-v1 | C99: MUL-ICON-TIMBER-PO | D99: File Transfer
A100: 99 | B100: customer-document-papi-v1 | C100: MUL-SWISSPOST | D100: File Transfer
A101: 100 | B101: icon-sftp-sapi-v1 | C101: MUL-SWISSPOST | D101: File Transfer
A102: 101 | B102: felix-sftp-sapi-v1 | C102: MUL-SWISSPOST | D102: File Transfer
A103: 102 | B103: hx-sftp-sapi-v1 | C103: MUL-SWISSPOST | D103: File Transfer
A104: 103 | B104: swisspost-sapi-v1 | C104: MUL-SWISSPOST | D104: File Transfer
A105: 104 | B105: columbus-document-sapi-v1 | C105: MUL-SWISSPOST | D105: File Transfer
A106: 105 | B106: timber-papi-v1 | C106: MUL-TIMBERSUPPLIERS | D106: Mixed | E106: UAT pending
...

Sheet All-Prod-MuleApps
A1: Sr No | B1: MuleSoft Applications | C1: Prod Status | D1: Comments | E1: Normalised name | F1: Integration | G1: Medium
A2: 1 | B2: starkuk-live-sfdc-accounts-sapi-v1 | C2: Started | E2: sfdc-accounts-sapi-v1 | F2: =VLOOKUP(E2,'MuleApps<=>MuleIntegrations'!B:C,2,FALSE) -> MUL-CONSENT | G2: =VLOOKUP(E2,'MuleApps<=>MuleIntegrations'!B:D,3,FALSE) -> Mixed
A3: 2 | B3: starkuk-live-wesupply-sftp-sapi-v1 | C3: Started | E3: wesupply-sftp-sapi-v1 | F3: =VLOOKUP(E3,'MuleApps<=>MuleIntegrations'!B:C,2,FALSE) -> MUL-SUPPLIER-PO | G3: =VLOOKUP(E3,'MuleApps<=>MuleIntegrations'!B:D,3,FALSE) -> File Transfer
A4: 3 | B4: sgbd-live-azure-blob-storage-sapi-v1 | C4: Started | E4: azure-blob-storage-sapi-v1 | F4: =VLOOKUP(E4,'MuleApps<=>MuleIntegrations'!B:C,2,FALSE) -> MUL-DIGITALASSET | G4: =VLOOKUP(E4,'MuleApps<=>MuleIntegrations'!B:D,3,FALSE) -> API
A5: 4 | B5: starkuk-live-icov-customersftp-sapi-v1 | C5: Started | E5: icov-customersftp-sapi-v1 | F5: =VLOOKUP(E5,'MuleApps<=>MuleIntegrations'!B:C,2,FALSE) -> MUL-CUSTORDERVALIDATION | G5: =VLOOKUP(E5,'MuleApps<=>MuleIntegrations'!B:D,3,FALSE) -> Mixed
A6: 5 | B6: starkuk-live-ovm-services-eapi-v1 | C6: Started | E6: ovm-services-eapi-v1 | F6: =VLOOKUP(E6,'MuleApps<=>MuleIntegrations'!B:C,2,FALSE) -> MUL-OPCARDS | G6: =VLOOKUP(E6,'MuleApps<=>MuleIntegrations'!B:D,3,FALSE) -> API
A7: 6 | B7: starkuk-live-bi-papi-v1 | C7: Undeployed | E7: bi-papi-v1 | F7: =VLOOKUP(E7,'MuleApps<=>MuleIntegrations'!B:C,2,FALSE) -> MUL-DATALAKE | G7: =VLOOKUP(E7,'MuleApps<=>MuleIntegrations'!B:D,3,FALSE) -> File Transfer
A8: 7 | B8: starkuk-live-icon-contact-eapi-v1 | C8: Started | E8: icon-contact-eapi-v1 | F8: =VLOOKUP(E8,'MuleApps<=>MuleIntegrations'!B:C,2,FALSE) -> MUL-CONSENT | G8: =VLOOKUP(E8,'MuleApps<=>MuleIntegrations'!B:D,3,FALSE) -> Mixed
A9: 8 | B9: starkuk-live-icon-contact-sapi-v1 | C9: Started | E9: icon-contact-sapi-v1 | F9: =VLOOKUP(E9,'MuleApps<=>MuleIntegrations'!B:C,2,FALSE) -> MUL-CONSENT | G9: =VLOOKUP(E9,'MuleApps<=>MuleIntegrations'!B:D,3,FALSE) -> Mixed
A10: 9 | B10: starkuk-live-po-proposal-papi-v1 | C10: Started | E10: po-proposal-papi-v1 | F10: =VLOOKUP(E10,'MuleApps<=>MuleIntegrations'!B:C,2,FALSE) -> MUL-INVENTORYAUTOMATION | G10: =VLOOKUP(E10,'MuleApps<=>MuleIntegrations'!B:D,3,FALSE) -> Mixed
A11: 10 | B11: starkuk-live-icon-account-sapi-v1 | C11: Started | E11: icon-account-sapi-v1 | F11: =VLOOKUP(E11,'MuleApps<=>MuleIntegrations'!B:C,2,FALSE) -> MUL-ACCOUNT-VALIDATION | G11: =VLOOKUP(E11,'MuleApps<=>MuleIntegrations'!B:D,3,FALSE) -> Mixed
A12: 11 | B12: starkuk-live-icon-product-sapi-v1 | C12: Started | E12: icon-product-sapi-v1 | F12: =VLOOKUP(E12,'MuleApps<=>MuleIntegrations'!B:C,2,FALSE) -> MUL-PUNCHOUT | G12: =VLOOKUP(E12,'MuleApps<=>MuleIntegrations'!B:D,3,FALSE) -> API
A13: 12 | B13: starkuk-live-product-sapi-v2 | C13: Started | E13: product-sapi-v2 | F13: =VLOOKUP(E13,'MuleApps<=>MuleIntegrations'!B:C,2,FALSE) -> MUL-PRODUCTS | G13: =VLOOKUP(E13,'MuleApps<=>MuleIntegrations'!B:D,3,FALSE) -> API
... A112: 111 | B112: starkuk-prod-cognito-sapi-v1 | C112: Started | E112: cognito-sapi-v1 | F112: =VLOOKUP(E112,'MuleApps<=>MuleIntegrations'!B:C,2,FALSE) -> MUL-FLEETWAVE-ICON-COGNITO | G112: =VLOOKUP(E112,'MuleApps<=>MuleIntegrations'!B:D,3,FALSE) -> Mixed

Sheet All-Prod-Mule-Triggers
A1: Sr No | B1: MuleSoft Applications | C1: TriggerName | D1: Scheduletime | E1: Prod Status | F1: Comments | G1: Normalised name | H1: Integration | I1: Medium
A2: 1 | B2: starkuk-live-pmsolutions-papi-v1 | C2: icon-to-pmsolutions-papi-flow_Scheduler | D2: 0 0 9,10 ? * * | E2: Enabled | G2: pmsolutions-papi-v1 | H2: =VLOOKUP(G2,'MuleApps<=>MuleIntegrations'!B:C,2,FALSE) -> MUL-MINSTER-NEW-ACCS | I2: =VLOOKUP(G2,'MuleApps<=>MuleIntegrations'!B:D,3,FALSE) -> File Transfer
A3: 2 | B3: starkuk-live-pmsolutions-papi-v1 | C3: outbound-reprocessing-scheduler-flow_Scheduler | D3: 0 30 9 ? * * | E3: Enabled | G3: pmsolutions-papi-v1 | H3: =VLOOKUP(G3,'MuleApps<=>MuleIntegrations'!B:C,2,FALSE) -> MUL-MINSTER-NEW-ACCS | I3: =VLOOKUP(G3,'MuleApps<=>MuleIntegrations'!B:D,3,FALSE) -> File Transfer
A4: 3 | B4: starkuk-live-bi-papi-v1 | C4: clear-token-scheduler_Scheduler | D4: 0 0 2 * * ? * | E4: Enabled | G4: bi-papi-v1 | H4: =VLOOKUP(G4,'MuleApps<=>MuleIntegrations'!B:C,2,FALSE) -> MUL-DATALAKE | I4: =VLOOKUP(G4,'MuleApps<=>MuleIntegrations'!B:D,3,FALSE) -> File Transfer
A5: 4 | B5: starkuk-live-bi-papi-v1 | C5: hx-org-grn-scheduler_org and grn files | E5: Disabled | G5: bi-papi-v1 | H5: =VLOOKUP(G5,'MuleApps<=>MuleIntegrations'!B:C,2,FALSE) -> MUL-DATALAKE | I5: =VLOOKUP(G5,'MuleApps<=>MuleIntegrations'!B:D,3,FALSE) -> File Transfer
A6: 5 | B6: starkuk-live-bi-papi-v1 | C6: hx-term-scheduler_Term files | E6: Disabled | G6: bi-papi-v1 | H6: =VLOOKUP(G6,'MuleApps<=>MuleIntegrations'!B:C,2,FALSE) -> MUL-DATALAKE | I6: =VLOOKUP(G6,'MuleApps<=>MuleIntegrations'!B:D,3,FALSE) -> File Transfer
A7: 6 | B7: starkuk-live-bi-papi-v1 | C7: icon-BC_ICRP-scheduler_Scheduler | E7: Disabled | G7: bi-papi-v1 | H7: =VLOOKUP(G7,'MuleApps<=>MuleIntegrations'!B:C,2,FALSE) -> MUL-DATALAKE | I7: =VLOOKUP(G7,'MuleApps<=>MuleIntegrations'!B:D,3,FALSE) -> File Transfer
A8: 7 | B8: starkuk-live-bi-papi-v1 | C8: icon-mans-scheduler_Scheduler | E8: Disabled | G8: bi-papi-v1 | H8: =VLOOKUP(G8,'MuleApps<=>MuleIntegrations'!B:C,2,FALSE) -> MUL-DATALAKE | I8: =VLOOKUP(G8,'MuleApps<=>MuleIntegrations'!B:D,3,FALSE) -> File Transfer
A9: 8 | B9: starkuk-live-bi-papi-v1 | C9: icon-scheduler-for-product-additional-files_Scheduler | E9: Disabled | G9: bi-papi-v1 | H9: =VLOOKUP(G9,'MuleApps<=>MuleIntegrations'!B:C,2,FALSE) -> MUL-DATALAKE | I9: =VLOOKUP(G9,'MuleApps<=>MuleIntegrations'!B:D,3,FALSE) -> File Transfer
A10: 9 | B10: starkuk-live-bi-papi-v1 | C10: icon-scheduler-for-supplier-additional-files_Scheduler | E10: Disabled | G10: bi-papi-v1 | H10: =VLOOKUP(G10,'MuleApps<=>MuleIntegrations'!B:C,2,FALSE) -> MUL-DATALAKE | I10: =VLOOKUP(G10,'MuleApps<=>MuleIntegrations'!B:D,3,FALSE) -> File Transfer
A11: 10 | B11: starkuk-live-bi-papi-v1 | C11: icon-scheduler_Scheduler | E11: Disabled | G11: bi-papi-v1 | H11: =VLOOKUP(G11,'MuleApps<=>MuleIntegrations'!B:C,2,FALSE) -> MUL-DATALAKE | I11: =VLOOKUP(G11,'MuleApps<=>MuleIntegrations'!B:D,3,FALSE) -> File Transfer
A12: 11 | B12: starkuk-live-bi-papi-v1 | C12: phocas-scheduler_Scheduler | E12: Disabled | G12: bi-papi-v1 | H12: =VLOOKUP(G12,'MuleApps<=>MuleIntegrations'!B:C,2,FALSE) -> MUL-DATALAKE | I12: =VLOOKUP(G12,'MuleApps<=>MuleIntegrations'!B:D,3,FALSE) -> File Transfer
A13: 12 | B13: starkuk-live-bi-papi-v1 | C13: send-token-scheduler_Scheduler | D13: 0 0/30 0-1,6,17-23 * * ? | E13: Enabled | G13: bi-papi-v1 | H13: =VLOOKUP(G13,'MuleApps<=>MuleIntegrations'!B:C,2,FALSE) -> MUL-DATALAKE | I13: =VLOOKUP(G13,'MuleApps<=>MuleIntegrations'!B:D,3,FALSE) -> File Transfer
A14: 13 | B14: starkuk-live-timber-papi-v1 | C14: felix-to-azure-scheduler-flow_felix-to-azure-scheduler | E14: Disabled | G14: timber-papi-v1 | H14: =VLOOKUP(G14,'MuleApps<=>MuleIntegrations'!B:C,2,FALSE) -> MUL-TIMBERDATABASE | I14: =VLOOKUP(G14,'MuleApps<=>MuleIntegrations'!B:D,3,FALSE) -> File Transfer
A15: 14 | B15: starkuk-live-timber-papi-v1 | C15: icon-to-felix-scheduler-flow_icon-felix-scheduler | E15: Disabled | G15: timber-papi-v1 | H15: =VLOOKUP(G15,'MuleApps<=>MuleIntegrations'!B:C,2,FALSE) -> MUL-TIMBERDATABASE | I15: =VLOOKUP(G15,'MuleApps<=>MuleIntegrations'!B:D,3,FALSE) -> File Transfer
A16: 15 | B16: starkuk-live-timber-papi-v1 | C16: timber-to-felix-scheduler-flow_timber-felix-scheduler | E16: Disabled | G16: timber-papi-v1 | H16: =VLOOKUP(G16,'MuleApps<=>MuleIntegrations'!B:C,2,FALSE) -> MUL-TIMBERDATABASE | I16: =VLOOKUP(G16,'MuleApps<=>MuleIntegrations'!B:D,3,FALSE) -> File Transfer
A17: 16 | B17: starkuk-live-ovm-papi-v1 | C17: ovm-papi-main-scheduler-flow_Scheduler | D17: 0 0/30 6-19 ? * MON,TUE,WED,THU,FRI,SAT * | E17: Enabled | G17: ovm-papi-v1 | H17: =VLOOKUP(G17,'MuleApps<=>MuleIntegrations'!B:C,2,FALSE) -> MUL-CUSTORDERVALIDATION | I17: =VLOOKUP(G17,'MuleApps<=>MuleIntegrations'!B:D,3,FALSE) -> Mixed
A18: 17 | B18: starkuk-live-ovm-papi-v1 | C18: ovm-papi-reprocessing-scheduler-flow_Scheduler | D18: 0 0/15 * ? * * * | E18: Enabled | G18: ovm-papi-v1 | H18: =VLOOKUP(G18,'MuleApps<=>MuleIntegrations'!B:C,2,FALSE) -> MUL-CUSTORDERVALIDATION | I18: =VLOOKUP(G18,'MuleApps<=>MuleIntegrations'!B:D,3,FALSE) -> Mixed
A19: 18 | B19: starkuk-live-ovm-papi-v1 | C19: ovm-papi-start-of-the-day-scheduler-flow_Scheduler | D19: 0 0 8 ? * * * | E19: Enabled | G19: ovm-papi-v1 | H19: =VLOOKUP(G19,'MuleApps<=>MuleIntegrations'!B:C,2,FALSE) -> MUL-CUSTORDERVALIDATION | I19: =VLOOKUP(G19,'MuleApps<=>MuleIntegrations'!B:D,3,FALSE) -> Mixed
A20: 19 | B20: starkuk-live-bi-papi-v2 | C20: felix-to-salesi-via-outbound-proxy-sapi_felix-to-salesi | E20: Disabled | G20: bi-papi-v2 | H20: =VLOOKUP(G20,'MuleApps<=>MuleIntegrations'!B:C,2,FALSE) -> MUL-ERP-3rd-PARTY | I20: =VLOOKUP(G20,'MuleApps<=>MuleIntegrations'!B:D,3,FALSE) -> File Transfer
A21: 20 | B21: starkuk-live-bi-papi-v2 | C21: hx-dumps-to-internal-flow_hx-dumps-to-internal | E21: Disabled | G21: bi-papi-v2 | H21: =VLOOKUP(G21,'MuleApps<=>MuleIntegrations'!B:C,2,FALSE) -> MUL-ERP-3rd-PARTY | I21: =VLOOKUP(G21,'MuleApps<=>MuleIntegrations'!B:D,3,FALSE) -> File Transfer
A22: 21 | B22: starkuk-live-bi-papi-v2 | C22: hx-informatica-to-internal-sftp-flow_scheduler | E22: Disabled | G22: bi-papi-v2 | H22: =VLOOKUP(G22,'MuleApps<=>MuleIntegrations'!B:C,2,FALSE) -> MUL-ERP-3rd-PARTY | I22: =VLOOKUP(G22,'MuleApps<=>MuleIntegrations'!B:D,3,FALSE) -> File Transfer
A23: 22 | B23: starkuk-live-bi-papi-v2 | C23: hx-to-concur-flow_hx-concur-scheduler | D23: 0 0 18 * * ? * | E23: Enabled | G23: bi-papi-v2 | H23: =VLOOKUP(G23,'MuleApps<=>MuleIntegrations'!B:C,2,FALSE) -> MUL-ERP-3rd-PARTY | I23: =VLOOKUP(G23,'MuleApps<=>MuleIntegrations'!B:D,3,FALSE) -> File Transfer
A24: 23 | B24: starkuk-live-bi-papi-v2 | C24: hx-to-dbm-flow_hx-to-dbm-scheduler | E24: Disabled | G24: bi-papi-v2 | H24: =VLOOKUP(G24,'MuleApps<=>MuleIntegrations'!B:C,2,FALSE) -> MUL-ERP-3rd-PARTY | I24: =VLOOKUP(G24,'MuleApps<=>MuleIntegrations'!B:D,3,FALSE) -> File Transfer
A25: 24 | B25: starkuk-live-bi-papi-v2 | C25: hx-to-internal-sftp-sapi-flow_hx-to-internal | E25: Disabled | G25: bi-papi-v2 | H25: =VLOOKUP(G25,'MuleApps<=>MuleIntegrations'!B:C,2,FALSE) -> MUL-ERP-3rd-PARTY | I25: =VLOOKUP(G25,'MuleApps<=>MuleIntegrations'!B:D,3,FALSE) -> File Transfer
A26: 25 | B26: starkuk-live-bi-papi-v2 | C26: hx-to-proactis-via-outbound-proxy-sapi-flow_Scheduler | E26: Disabled | G26: bi-papi-v2 | H26: =VLOOKUP(G26,'MuleApps<=>MuleIntegrations'!B:C,2,FALSE) -> MUL-ERP-3rd-PARTY | I26: =VLOOKUP(G26,'MuleApps<=>MuleIntegrations'!B:D,3,FALSE) -> File Transfer
A27: 26 | B27: starkuk-live-bi-papi-v2 | C27: icon-account-handler-cash-flow_Scheduler | E27: Disabled | G27: bi-papi-v2 | H27: =VLOOKUP(G27,'MuleApps<=>MuleIntegrations'!B:C,2,FALSE) -> MUL-ERP-3rd-PARTY | I27: =VLOOKUP(G27,'MuleApps<=>MuleIntegrations'!B:D,3,FALSE) -> File Transfer
A28: 27 | B28: starkuk-live-bi-papi-v2 | C28: icon-account-handler-credit-flow_Scheduler | E28: Disabled | G28: bi-papi-v2 | H28: =VLOOKUP(G28,'MuleApps<=>MuleIntegrations'!B:C,2,FALSE) -> MUL-ERP-3rd-PARTY | I28: =VLOOKUP(G28,'MuleApps<=>MuleIntegrations'!B:D,3,FALSE) -> File Transfer
A29: 28 | B29: starkuk-live-bi-papi-v2 | C29: icon-account-handler-marketing-flow_Scheduler | E29: Disabled | G29: bi-papi-v2 | H29: =VLOOKUP(G29,'MuleApps<=>MuleIntegrations'!B:C,2,FALSE) -> MUL-ERP-3rd-PARTY | I29: =VLOOKUP(G29,'MuleApps<=>MuleIntegrations'!B:D,3,FALSE) -> File Transfer
A30: 29 | B30: starkuk-live-bi-papi-v2 | C30: icon-account-handler-reject-flow_Scheduler | E30: Disabled | G30: bi-papi-v2 | H30: =VLOOKUP(G30,'MuleApps<=>MuleIntegrations'!B:C,2,FALSE) -> MUL-ERP-3rd-PARTY | I30: =VLOOKUP(G30,'MuleApps<=>MuleIntegrations'!B:D,3,FALSE) -> File Transfer
A31: 30 | B31: starkuk-live-bi-papi-v2 | C31: icon-ecs-to-blob-flow_icon-ecs-to-stark-azure-blob | E31: Disabled | G31: bi-papi-v2 | H31: =VLOOKUP(G31,'MuleApps<=>MuleIntegrations'!B:C,2,FALSE) -> MUL-ERP-3rd-PARTY | I31: =VLOOKUP(G31,'MuleApps<=>MuleIntegrations'!B:D,3,FALSE) -> File Transfer
A32: 31 | B32: starkuk-live-bi-papi-v2 | C32: icon-sql-to-internal-scheduler-flow_icon-sql-to-internal-scheduler | E32: Disabled | G32: bi-papi-v2 | H32: =VLOOKUP(G32,'MuleApps<=>MuleIntegrations'!B:C,2,FALSE) -> MUL-ERP-3rd-PARTY | I32: =VLOOKUP(G32,'MuleApps<=>MuleIntegrations'!B:D,3,FALSE) -> File Transfer
A33: 32 | B33: starkuk-live-bi-papi-v2 | C33: icon-to-insight-flow_Scheduler | E33: Disabled | G33: bi-papi-v2 | H33: =VLOOKUP(G33,'MuleApps<=>MuleIntegrations'!B:C,2,FALSE) -> MUL-ERP-3rd-PARTY | I33: =VLOOKUP(G33,'MuleApps<=>MuleIntegrations'!B:D,3,FALSE) -> File Transfer
A34: 33 | B34: starkuk-live-bi-papi-v2 | C34: internal-to-icertis-flow_internal-to-icertis | E34: Disabled | G34: bi-papi-v2 | H34: =VLOOKUP(G34,'MuleApps<=>MuleIntegrations'!B:C,2,FALSE) -> MUL-ERP-3rd-PARTY | I34: =VLOOKUP(G34,'MuleApps<=>MuleIntegrations'!B:D,3,FALSE) -> File Transfer
A35: 34 | B35: starkuk-live-bi-papi-v2 | C35: internal-to-insight-flow_internal-to-insight-scheduler | E35: Disabled | G35: bi-papi-v2 | H35: =VLOOKUP(G35,'MuleApps<=>MuleIntegrations'!B:C,2,FALSE) -> MUL-ERP-3rd-PARTY | I35: =VLOOKUP(G35,'MuleApps<=>MuleIntegrations'!B:D,3,FALSE) -> File Transfer
A36: 35 | B36: starkuk-live-bi-papi-v2 | C36: stark-azure-to-insight-flow_stark-azure-to-insight-scheduler | E36: Disabled | G36: bi-papi-v2 | H36: =VLOOKUP(G36,'MuleApps<=>MuleIntegrations'!B:C,2,FALSE) -> MUL-ERP-3rd-PARTY | I36: =VLOOKUP(G36,'MuleApps<=>MuleIntegrations'!B:D,3,FALSE) -> File Transfer
A37: 36 | B37: starkuk-live-columbus-document-papi-v1 | C37: cognizant-sftp-to-columbus-blob-schedule_cognizant-to-columbus | D37: 0 1 0 ? * * * | E37: Enabled | G37: columbus-document-papi-v1 | H37: =VLOOKUP(G37,'MuleApps<=>MuleIntegrations'!B:C,2,FALSE) -> MUL-CONSOLIDATEDINVOICE | I37: =VLOOKUP(G37,'MuleApps<=>MuleIntegrations'!B:D,3,FALSE) -> Mixed
A38: 37 | B38: starkuk-live-columbus-document-papi-v1 | C38: felix-to-columbus-flow_felix-to-columbus-scheduler | E38: Disabled | G38: columbus-document-papi-v1 | H38: =VLOOKUP(G38,'MuleApps<=>MuleIntegrations'!B:C,2,FALSE) -> MUL-CONSOLIDATEDINVOICE | I38: =VLOOKUP(G38,'MuleApps<=>MuleIntegrations'!B:D,3,FALSE) -> Mixed
A39: 38 | B39: starkuk-live-columbus-document-papi-v1 | C39: felix-to-stark-azure-and-columbus-flow_Scheduler | E39: Disabled | G39: columbus-document-papi-v1 | H39: =VLOOKUP(G39,'MuleApps<=>MuleIntegrations'!B:C,2,FALSE) -> MUL-CONSOLIDATEDINVOICE | I39: =VLOOKUP(G39,'MuleApps<=>MuleIntegrations'!B:D,3,FALSE) -> Mixed
A40: 39 | B40: starkuk-live-columbus-document-papi-v1 | C40: hx-to-columbus-flow_hx-to-columbus-scheduler | E40: Disabled | G40: columbus-document-papi-v1 | H40: =VLOOKUP(G40,'MuleApps<=>MuleIntegrations'!B:C,2,FALSE) -> MUL-CONSOLIDATEDINVOICE | I40: =VLOOKUP(G40,'MuleApps<=>MuleIntegrations'!B:D,3,FALSE) -> Mixed
A41: 40 | B41: starkuk-live-columbus-document-papi-v1 | C41: hx-to-stark-azure-and-columbus-flow_Scheduler | D41: 0 50 */1 ? * * | E41: Enabled | G41: columbus-document-papi-v1 | H41: =VLOOKUP(G41,'MuleApps<=>MuleIntegrations'!B:C,2,FALSE) -> MUL-CONSOLIDATEDINVOICE | I41: =VLOOKUP(G41,'MuleApps<=>MuleIntegrations'!B:D,3,FALSE) -> Mixed
A42: 41 | B42: starkuk-live-columbus-document-papi-v1 | C42: hybris-to-columbus-flow_hybris-to-columbus-scheduler | E42: Disabled | G42: columbus-document-papi-v1 | H42: =VLOOKUP(G42,'MuleApps<=>MuleIntegrations'!B:C,2,FALSE) -> MUL-CONSOLIDATEDINVOICE | I42: =VLOOKUP(G42,'MuleApps<=>MuleIntegrations'!B:D,3,FALSE) -> Mixed
A43: 42 | B43: starkuk-live-columbus-document-papi-v1 | C43: icon-to-columbus-flow_icon-to-columbus-scheduler | E43: Disabled | G43: columbus-document-papi-v1 | H43: =VLOOKUP(G43,'MuleApps<=>MuleIntegrations'!B:C,2,FALSE) -> MUL-CONSOLIDATEDINVOICE | I43: =VLOOKUP(G43,'MuleApps<=>MuleIntegrations'!B:D,3,FALSE) -> Mixed
A44: 43 | B44: starkuk-live-columbus-document-papi-v1 | C44: redflag-to-columbus-reprocessing-flow_Scheduler | D44: 0 */5 * ? * * | E44: Enabled | G44: columbus-document-papi-v1 | H44: =VLOOKUP(G44,'MuleApps<=>MuleIntegrations'!B:C,2,FALSE) -> MUL-CONSOLIDATEDINVOICE | I44: =VLOOKUP(G44,'MuleApps<=>MuleIntegrations'!B:D,3,FALSE) -> Mixed
A45: 44 | B45: starkuk-live-columbus-document-papi-v1 | C45: stark-azure-to-hx-flow_Scheduler | D45: 0 16 */1 ? * * | E45: Enabled | G45: columbus-document-papi-v1 | H45: =VLOOKUP(G45,'MuleApps<=>MuleIntegrations'!B:C,2,FALSE) -> MUL-CONSOLIDATEDINVOICE | I45: =VLOOKUP(G45,'MuleApps<=>MuleIntegrations'!B:D,3,FALSE) -> Mixed
A46: 45 | B46: starkuk-live-phocas-cloud-papi-v1 | C46: clear-object-store-flow_Scheduler | D46: 0 0 2 * * ? * | E46: Enabled | G46: phocas-cloud-papi-v1 | H46: =VLOOKUP(G46,'MuleApps<=>MuleIntegrations'!B:C,2,FALSE) -> MUL-ICERTIS | I46: =VLOOKUP(G46,'MuleApps<=>MuleIntegrations'!B:D,3,FALSE) -> File Transfer
A47: 46 | B47: starkuk-live-phocas-cloud-papi-v1 | C47: debt-refactoring-azure-token-scheduler_Scheduler | D47: 0 0 5,6 ? * * * | E47: Enabled | G47: phocas-cloud-papi-v1 | H47: =VLOOKUP(G47,'MuleApps<=>MuleIntegrations'!B:C,2,FALSE) -> MUL-ICERTIS | I47: =VLOOKUP(G47,'MuleApps<=>MuleIntegrations'!B:D,3,FALSE) -> File Transfer
A48: 47 | B48: starkuk-live-phocas-cloud-papi-v1 | C48: hx-credit-control-to-phocas-flow_scheduler | E48: Disabled | G48: phocas-cloud-papi-v1 | H48: =VLOOKUP(G48,'MuleApps<=>MuleIntegrations'!B:C,2,FALSE) -> MUL-ICERTIS | I48: =VLOOKUP(G48,'MuleApps<=>MuleIntegrations'!B:D,3,FALSE) -> File Transfer
A49: 48 | B49: starkuk-live-phocas-cloud-papi-v1 | C49: hx-informatica-to-phocas-flow_scheduler | E49: Disabled | G49: phocas-cloud-papi-v1 | H49: =VLOOKUP(G49,'MuleApps<=>MuleIntegrations'!B:C,2,FALSE) -> MUL-ICERTIS | I49: =VLOOKUP(G49,'MuleApps<=>MuleIntegrations'!B:D,3,FALSE) -> File Transfer
A50: 49 | B50: starkuk-live-phocas-cloud-papi-v1 | C50: hx-to-dbm-and-insight-reprocessing-flow_Scheduler | E50: Disabled | G50: phocas-cloud-papi-v1 | H50: =VLOOKUP(G50,'MuleApps<=>MuleIntegrations'!B:C,2,FALSE) -> MUL-ICERTIS | I50: =VLOOKUP(G50,'MuleApps<=>MuleIntegrations'!B:D,3,FALSE) -> File Transfer
A51: 50 | B51: starkuk-live-phocas-cloud-papi-v1 | C51: hx-to-phocas-custval-scheduler_hx-phocas-scheduler | E51: Disabled | G51: phocas-cloud-papi-v1 | H51: =VLOOKUP(G51,'MuleApps<=>MuleIntegrations'!B:C,2,FALSE) -> MUL-ICERTIS | I51: =VLOOKUP(G51,'MuleApps<=>MuleIntegrations'!B:D,3,FALSE) -> File Transfer
A52: 51 | B52: starkuk-live-phocas-cloud-papi-v1 | C52: hx-to-phocas-sales-customers-suppliers-scheduler_Poll | E52: Disabled | G52: phocas-cloud-papi-v1 | H52: =VLOOKUP(G52,'MuleApps<=>MuleIntegrations'!B:C,2,FALSE) -> MUL-ICERTIS | I52: =VLOOKUP(G52,'MuleApps<=>MuleIntegrations'!B:D,3,FALSE) -> File Transfer
A53: 52 | B53: starkuk-live-phocas-cloud-papi-v1 | C53: icertis-to-phocas-scheduler_icertis-to-phocas | E53: Disabled | G53: phocas-cloud-papi-v1 | H53: =VLOOKUP(G53,'MuleApps<=>MuleIntegrations'!B:C,2,FALSE) -> MUL-ICERTIS | I53: =VLOOKUP(G53,'MuleApps<=>MuleIntegrations'!B:D,3,FALSE) -> File Transfer
A54: 53 | B54: starkuk-live-phocas-cloud-papi-v1 | C54: icon(phocas)-to-phocas-reprocessing-flow_Scheduler | D54: 0 30 3 ? * * * | E54: Enabled | G54: phocas-cloud-papi-v1 | H54: =VLOOKUP(G54,'MuleApps<=>MuleIntegrations'!B:C,2,FALSE) -> MUL-ICERTIS | I54: =VLOOKUP(G54,'MuleApps<=>MuleIntegrations'!B:D,3,FALSE) -> File Transfer
A55: 54 | B55: starkuk-live-phocas-cloud-papi-v1 | C55: icon(phocas)-to-phocas-scheduler_Scheduler | E55: Disabled | G55: phocas-cloud-papi-v1 | H55: =VLOOKUP(G55,'MuleApps<=>MuleIntegrations'!B:C,2,FALSE) -> MUL-ICERTIS | I55: =VLOOKUP(G55,'MuleApps<=>MuleIntegrations'!B:D,3,FALSE) -> File Transfer
A56: 55 | B56: starkuk-live-phocas-cloud-papi-v1 | C56: icon(phocas-manual)-to-phocas-scheduler-flow_icon-phocas-manual-to-phocas-scheduler | E56: Disabled | G56: phocas-cloud-papi-v1 | H56: =VLOOKUP(G56,'MuleApps<=>MuleIntegrations'!B:C,2,FALSE) -> MUL-ICERTIS | I56: =VLOOKUP(G56,'MuleApps<=>MuleIntegrations'!B:D,3,FALSE) -> File Transfer
A57: 56 | B57: starkuk-live-phocas-cloud-papi-v1 | C57: icon(sql)-to-phocas-scheduler_icon-phocas-scheduler | E57: Disabled | G57: phocas-cloud-papi-v1 | H57: =VLOOKUP(G57,'MuleApps<=>MuleIntegrations'!B:C,2,FALSE) -> MUL-ICERTIS | I57: =VLOOKUP(G57,'MuleApps<=>MuleIntegrations'!B:D,3,FALSE) -> File Transfer
A58: 57 | B58: starkuk-live-phocas-cloud-papi-v1 | C58: icon-credit-control-to-phocas-flow_scheduler | E58: Disabled | G58: phocas-cloud-papi-v1 | H58: =VLOOKUP(G58,'MuleApps<=>MuleIntegrations'!B:C,2,FALSE) -> MUL-ICERTIS | I58: =VLOOKUP(G58,'MuleApps<=>MuleIntegrations'!B:D,3,FALSE) -> File Transfer
A59: 58 | B59: starkuk-live-phocas-cloud-papi-v1 | C59: icon-finance-debt-refactoring_Scheduler | E59: Disabled | G59: phocas-cloud-papi-v1 | H59: =VLOOKUP(G59,'MuleApps<=>MuleIntegrations'!B:C,2,FALSE) -> MUL-ICERTIS | I59: =VLOOKUP(G59,'MuleApps<=>MuleIntegrations'!B:D,3,FALSE) -> File Transfer
A60: 59 | B60: starkuk-live-phocas-cloud-papi-v1 | C60: phocas-azure-token-scheduler_Scheduler | D60: 0 0/30 5-9 * * ? | E60: Enabled | G60: phocas-cloud-papi-v1 | H60: =VLOOKUP(G60,'MuleApps<=>MuleIntegrations'!B:C,2,FALSE) -> MUL-ICERTIS | I60: =VLOOKUP(G60,'MuleApps<=>MuleIntegrations'!B:D,3,FALSE) -> File Transfer
A61: 60 | B61: starkuk-live-phocas-cloud-papi-v1 | C61: phocas-to-azure-scheduler_Scheduler | E61: Disabled | G61: phocas-cloud-papi-v1 | H61: =VLOOKUP(G61,'MuleApps<=>MuleIntegrations'!B:C,2,FALSE) -> MUL-ICERTIS | I61: =VLOOKUP(G61,'MuleApps<=>MuleIntegrations'!B:D,3,FALSE) -> File Transfer
A62: 61 | B62: starkuk-live-phocas-cloud-papi-v1 | C62: phocas-to-dbm-scheduler_Scheduler | E62: Disabled | G62: phocas-cloud-papi-v1 | H62: =VLOOKUP(G62,'MuleApps<=>MuleIntegrations'!B:C,2,FALSE) -> MUL-ICERTIS | I62: =VLOOKUP(G62,'MuleApps<=>MuleIntegrations'!B:D,3,FALSE) -> File Transfer
A63: 62 | B63: starkuk-live-quote-papi-v1 | C63: quote-papi-post-orders-icon-to-salesforce-scheduler-flow_Scheduler | E63: Disabled | G63: quote-papi-v1 | H63: =VLOOKUP(G63,'MuleApps<=>MuleIntegrations'!B:C,2,FALSE) -> MUL-SALES-PIPELINE | I63: =VLOOKUP(G63,'MuleApps<=>MuleIntegrations'!B:D,3,FALSE) -> Mixed
A64: 63 | B64: starkuk-live-quote-papi-v1 | C64: quote-papi-post-quotes-icon-to-salesforce-scheduler-flow_Scheduler | E64: Disabled | G64: quote-papi-v1 | H64: =VLOOKUP(G64,'MuleApps<=>MuleIntegrations'!B:C,2,FALSE) -> MUL-SALES-PIPELINE | I64: =VLOOKUP(G64,'MuleApps<=>MuleIntegrations'!B:D,3,FALSE) -> Mixed
A65: 64 | B65: starkuk-live-customer-document-papi-v1 | C65: columbus-scheduler_icon-columbus-scheduler | E65: Disabled | G65: customer-document-papi-v1 | H65: =VLOOKUP(G65,'MuleApps<=>MuleIntegrations'!B:C,2,FALSE) -> MUL-CONSOLIDATEDINVOICE | I65: =VLOOKUP(G65,'MuleApps<=>MuleIntegrations'!B:D,3,FALSE) -> Mixed
A66: 65 | B66: starkuk-live-customer-document-papi-v1 | C66: credit-chase-files-scheduler_credit chase files scheduler | D66: 0 0 * ? * * | E66: Enabled | G66: customer-document-papi-v1 | H66: =VLOOKUP(G66,'MuleApps<=>MuleIntegrations'!B:C,2,FALSE) -> MUL-CONSOLIDATEDINVOICE | I66: =VLOOKUP(G66,'MuleApps<=>MuleIntegrations'!B:D,3,FALSE) -> Mixed
A67: 66 | B67: starkuk-live-customer-document-papi-v1 | C67: felix-int-timber-to-swisspost_Felix Int Timber To Swisspost Scheduler | E67: Disabled | G67: customer-document-papi-v1 | H67: =VLOOKUP(G67,'MuleApps<=>MuleIntegrations'!B:C,2,FALSE) -> MUL-CONSOLIDATEDINVOICE | I67: =VLOOKUP(G67,'MuleApps<=>MuleIntegrations'!B:D,3,FALSE) -> Mixed
A68: 67 | B68: starkuk-live-customer-document-papi-v1 | C68: felix-timber-to-swisspost_Felix Timber To Swisspost Scheduler | D68: 0 0/15 6-8 * * ? * | E68: Enabled | G68: customer-document-papi-v1 | H68: =VLOOKUP(G68,'MuleApps<=>MuleIntegrations'!B:C,2,FALSE) -> MUL-CONSOLIDATEDINVOICE | I68: =VLOOKUP(G68,'MuleApps<=>MuleIntegrations'!B:D,3,FALSE) -> Mixed
A69: 68 | B69: starkuk-live-customer-document-papi-v1 | C69: hx-to-columbus-flow_Hx To Columbus Scheduler | E69: Disabled | G69: customer-document-papi-v1 | H69: =VLOOKUP(G69,'MuleApps<=>MuleIntegrations'!B:C,2,FALSE) -> MUL-CONSOLIDATEDINVOICE | I69: =VLOOKUP(G69,'MuleApps<=>MuleIntegrations'!B:D,3,FALSE) -> Mixed
A70: 69 | B70: starkuk-live-customer-document-papi-v1 | C70: hx-to-salesforce-schedule_hx-to-salesforce | D70: 0 30 0/1 ? * * * | E70: Enabled | G70: customer-document-papi-v1 | H70: =VLOOKUP(G70,'MuleApps<=>MuleIntegrations'!B:C,2,FALSE) -> MUL-CONSOLIDATEDINVOICE | I70: =VLOOKUP(G70,'MuleApps<=>MuleIntegrations'!B:D,3,FALSE) -> Mixed
A71: 70 | B71: starkuk-live-customer-document-papi-v1 | C71: hx-to-swisspost_Hx To Swisspost Scheduler | E71: Disabled | G71: customer-document-papi-v1 | H71: =VLOOKUP(G71,'MuleApps<=>MuleIntegrations'!B:C,2,FALSE) -> MUL-CONSOLIDATEDINVOICE | I71: =VLOOKUP(G71,'MuleApps<=>MuleIntegrations'!B:D,3,FALSE) -> Mixed
A72: 71 | B72: starkuk-live-customer-document-papi-v1 | C72: icon-to-swisspost-scheduler_icon to swisspost scheduler | E72: Disabled | G72: customer-document-papi-v1 | H72: =VLOOKUP(G72,'MuleApps<=>MuleIntegrations'!B:C,2,FALSE) -> MUL-CONSOLIDATEDINVOICE | I72: =VLOOKUP(G72,'MuleApps<=>MuleIntegrations'!B:D,3,FALSE) -> Mixed
A73: 72 | B73: starkuk-live-customer-document-papi-v1 | C73: reprocessing-credit-chase-files-scheduler_credit-chase-error-files-scheduler | D73: Every 30 minutes | E73: Enabled | G73: customer-document-papi-v1 | H73: =VLOOKUP(G73,'MuleApps<=>MuleIntegrations'!B:C,2,FALSE) -> MUL-CONSOLIDATEDINVOICE | I73: =VLOOKUP(G73,'MuleApps<=>MuleIntegrations'!B:D,3,FALSE) -> Mixed
A74: 73 | B74: starkuk-live-customer-document-papi-v1 | C74: swisspost-files-scheduler_swisspost files scheduler | D74: Every 10 minutes | E74: Enabled | G74: customer-document-papi-v1 | H74: =VLOOKUP(G74,'MuleApps<=>MuleIntegrations'!B:C,2,FALSE) -> MUL-CONSOLIDATEDINVOICE | I74: =VLOOKUP(G74,'MuleApps<=>MuleIntegrations'!B:D,3,FALSE) -> Mixed
A75: 74 | B75: starkuk-live-sales-papi-v1 | C75: sales-papi-get-quote-scheduler-flow_Scheduler | D75: Every hour | E75: Enabled | G75: sales-papi-v1 | H75: =VLOOKUP(G75,'MuleApps<=>MuleIntegrations'!B:C,2,FALSE) -> MUL-SALES-PIPELINE | I75: =VLOOKUP(G75,'MuleApps<=>MuleIntegrations'!B:D,3,FALSE) -> Mixed
A76: 75 | B76: starkuk-live-edi-papi-v1 | C76: felix-intl-timbre-to-truecommerce-flow_felix-intl-timbre-to-truecommerce | E76: Disabled | G76: edi-papi-v1 | H76: =VLOOKUP(G76,'MuleApps<=>MuleIntegrations'!B:C,2,FALSE) -> MUL-TRUECOMMERCE | I76: =VLOOKUP(G76,'MuleApps<=>MuleIntegrations'!B:D,3,FALSE) -> File Transfer
A77: 76 | B77: starkuk-live-edi-papi-v1 | C77: felix-timbre-group-to-truecommerce-flow_felix-timbre-group-to-truecommerce | D77: 0 0/30 7-9 ? * * * | E77: Enabled | G77: edi-papi-v1 | H77: =VLOOKUP(G77,'MuleApps<=>MuleIntegrations'!B:C,2,FALSE) -> MUL-TRUECOMMERCE | I77: =VLOOKUP(G77,'MuleApps<=>MuleIntegrations'!B:D,3,FALSE) -> File Transfer
A78: 77 | B78: starkuk-live-edi-papi-v1 | C78: hx-tradex-flow_hx-tradex | E78: Disabled | G78: edi-papi-v1 | H78: =VLOOKUP(G78,'MuleApps<=>MuleIntegrations'!B:C,2,FALSE) -> MUL-TRUECOMMERCE | I78: =VLOOKUP(G78,'MuleApps<=>MuleIntegrations'!B:D,3,FALSE) -> File Transfer
A79: 78 | B79: starkuk-live-edi-papi-v1 | C79: icon-imagedata-flow_icon-imagedata | E79: Disabled | G79: edi-papi-v1 | H79: =VLOOKUP(G79,'MuleApps<=>MuleIntegrations'!B:C,2,FALSE) -> MUL-TRUECOMMERCE | I79: =VLOOKUP(G79,'MuleApps<=>MuleIntegrations'!B:D,3,FALSE) -> File Transfer
A80: 79 | B80: starkuk-live-edi-papi-v1 | C80: icon-tradex-flow_iocn-tradex | E80: Disabled | G80: edi-papi-v1 | H80: =VLOOKUP(G80,'MuleApps<=>MuleIntegrations'!B:C,2,FALSE) -> MUL-TRUECOMMERCE | I80: =VLOOKUP(G80,'MuleApps<=>MuleIntegrations'!B:D,3,FALSE) -> File Transfer
A81: 80 | B81: starkuk-live-edi-papi-v1 | C81: icon-wesupply-primary-path-flow_icon-wesupply-primary-path | D81: Every 2 minutes | E81: Enabled | G81: edi-papi-v1 | H81: =VLOOKUP(G81,'MuleApps<=>MuleIntegrations'!B:C,2,FALSE) -> MUL-TRUECOMMERCE | I81: =VLOOKUP(G81,'MuleApps<=>MuleIntegrations'!B:D,3,FALSE) -> File Transfer
A82: 81 | B82: starkuk-live-edi-papi-v1 | C82: icon-wesupply-secondary-path-flow_icon-wesupply-secondary-path | D82: Every 2 minutes | E82: Enabled | G82: edi-papi-v1 | H82: =VLOOKUP(G82,'MuleApps<=>MuleIntegrations'!B:C,2,FALSE) -> MUL-TRUECOMMERCE | I82: =VLOOKUP(G82,'MuleApps<=>MuleIntegrations'!B:D,3,FALSE) -> File Transfer
A83: 82 | B83: starkuk-live-edi-papi-v1 | C83: Icon-wincanton-flow_Icon-wincanton | E83: Disabled | G83: edi-papi-v1 | H83: =VLOOKUP(G83,'MuleApps<=>MuleIntegrations'!B:C,2,FALSE) -> MUL-TRUECOMMERCE | I83: =VLOOKUP(G83,'MuleApps<=>MuleIntegrations'!B:D,3,FALSE) -> File Transfer
A84: 83 | B84: starkuk-live-edi-papi-v1 | C84: inbound-reprocesseing-scheduler-flow_Scheduler | D84: Every 30 minutes | E84: Enabled | G84: edi-papi-v1 | H84: =VLOOKUP(G84,'MuleApps<=>MuleIntegrations'!B:C,2,FALSE) -> MUL-TRUECOMMERCE | I84: =VLOOKUP(G84,'MuleApps<=>MuleIntegrations'!B:D,3,FALSE) -> File Transfer
A85: 84 | B85: starkuk-live-edi-papi-v1 | C85: outbound-reprocessing-schedulerFlow_Scheduler | D85: Every 30 minutes | E85: Enabled | G85: edi-papi-v1 | H85: =VLOOKUP(G85,'MuleApps<=>MuleIntegrations'!B:C,2,FALSE) -> MUL-TRUECOMMERCE | I85: =VLOOKUP(G85,'MuleApps<=>MuleIntegrations'!B:D,3,FALSE) -> File Transfer
A86: 85 | B86: starkuk-live-edi-papi-v1 | C86: tradex-icon-flow_tradex-icon | E86: Disabled | G86: edi-papi-v1 | H86: =VLOOKUP(G86,'MuleApps<=>MuleIntegrations'!B:C,2,FALSE) -> MUL-TRUECOMMERCE | I86: =VLOOKUP(G86,'MuleApps<=>MuleIntegrations'!B:D,3,FALSE) -> File Transfer
A87: 86 | B87: starkuk-live-edi-papi-v1 | C87: tradex-truecommerce-impl-flow_tradex-to-truecommerce | E87: Disabled | G87: edi-papi-v1 | H87: =VLOOKUP(G87,'MuleApps<=>MuleIntegrations'!B:C,2,FALSE) -> MUL-TRUECOMMERCE | I87: =VLOOKUP(G87,'MuleApps<=>MuleIntegrations'!B:D,3,FALSE) -> File Transfer
A88: 87 | B88: starkuk-live-edi-papi-v1 | C88: truecommerce-hx-flow_truecommerce-hx | E88: Disabled | G88: edi-papi-v1 | H88: =VLOOKUP(G88,'MuleApps<=>MuleIntegrations'!B:C,2,FALSE) -> MUL-TRUECOMMERCE | I88: =VLOOKUP(G88,'MuleApps<=>MuleIntegrations'!B:D,3,FALSE) -> File Transfer
A89: 88 | B89: starkuk-live-edi-papi-v1 | C89: truecommerce-icon-flow_truecommerce-icon | E89: Disabled | G89: edi-papi-v1 | H89: =VLOOKUP(G89,'MuleApps<=>MuleIntegrations'!B:C,2,FALSE) -> MUL-TRUECOMMERCE | I89: =VLOOKUP(G89,'MuleApps<=>MuleIntegrations'!B:D,3,FALSE) -> File Transfer
A90: 89 | B90: starkuk-live-edi-papi-v1 | C90: wesupply-icon-flow_wesupply-icon | D90: Every 5 minutes | E90: Enabled | G90: edi-papi-v1 | H90: =VLOOKUP(G90,'MuleApps<=>MuleIntegrations'!B:C,2,FALSE) -> MUL-TRUECOMMERCE | I90: =VLOOKUP(G90,'MuleApps<=>MuleIntegrations'!B:D,3,FALSE) -> File Transfer
A91: 90 | B91: starkuk-live-edi-papi-v1 | C91: wincanton-icon-flow_Scheduler | E91: Disabled | G91: edi-papi-v1 | H91: =VLOOKUP(G91,'MuleApps<=>MuleIntegrations'!B:C,2,FALSE) -> MUL-TRUECOMMERCE | I91: =VLOOKUP(G91,'MuleApps<=>MuleIntegrations'!B:D,3,FALSE) -> File Transfer
A92: 91 | B92: starkuk-live-customer-catalogue-papi-v1 | C92: customer-catalogue-papi-to-icon-flow_Scheduler | D92: Every 3 minutes | E92: Enabled | G92: customer-catalogue-papi-v1 | H92: =VLOOKUP(G92,'MuleApps<=>MuleIntegrations'!B:C,2,FALSE) -> MUL-PUNCHOUT | I92: =VLOOKUP(G92,'MuleApps<=>MuleIntegrations'!B:D,3,FALSE) -> API
A93: 92 | B93: starkuk-live-po-proposal-papi-v1 | C93: icon-relex-papi-flow_Scheduler | D93: 0 0/10 * * * ? | E93: Enabled | G93: po-proposal-papi-v1 | H93: =VLOOKUP(G93,'MuleApps<=>MuleIntegrations'!B:C,2,FALSE) -> MUL-INVENTORYAUTOMATION | I93: =VLOOKUP(G93,'MuleApps<=>MuleIntegrations'!B:D,3,FALSE) -> Mixed
A94: 93 | B94: starkuk-live-po-proposal-papi-v1 | C94: icon-relex-papi-reprocessing-flow_Scheduler | D94: 0 5 8-22 ? * MON-SAT * | E94: Enabled | G94: po-proposal-papi-v1 | H94: =VLOOKUP(G94,'MuleApps<=>MuleIntegrations'!B:C,2,FALSE) -> MUL-INVENTORYAUTOMATION | I94: =VLOOKUP(G94,'MuleApps<=>MuleIntegrations'!B:D,3,FALSE) -> Mixed
A95: 94 | B95: starkuk-live-po-proposal-papi-v1 | C95: po-proposal-papi-flow_Scheduler | D95: 0 0 8 * * ? * | E95: Enabled | G95: po-proposal-papi-v1 | H95: =VLOOKUP(G95,'MuleApps<=>MuleIntegrations'!B:C,2,FALSE) -> MUL-INVENTORYAUTOMATION | I95: =VLOOKUP(G95,'MuleApps<=>MuleIntegrations'!B:D,3,FALSE) -> Mixed
A96: 95 | B96: starkuk-live-po-proposal-papi-v1 | C96: relex-icon-papi-flow_Scheduler | D96: 0 15 9 ? * MON-FRI * | E96: Enabled | G96: po-proposal-papi-v1 | H96: =VLOOKUP(G96,'MuleApps<=>MuleIntegrations'!B:C,2,FALSE) -> MUL-INVENTORYAUTOMATION | I96: =VLOOKUP(G96,'MuleApps<=>MuleIntegrations'!B:D,3,FALSE) -> Mixed
A97: 96 | B97: starkuk-live-po-proposal-papi-v1 | C97: relex-no-file-notification-flow_Scheduler | D97: 0 30 11 ? * MON-FRI | E97: Enabled | G97: po-proposal-papi-v1 | H97: =VLOOKUP(G97,'MuleApps<=>MuleIntegrations'!B:C,2,FALSE) -> MUL-INVENTORYAUTOMATION | I97: =VLOOKUP(G97,'MuleApps<=>MuleIntegrations'!B:D,3,FALSE) -> Mixed
A98: 97 | B98: starkuk-live-po-proposal-papi-v1 | C98: stark-azure-no-file-notification-flow_Scheduler | D98: 0 30 10 ? * MON-FRI | E98: Enabled | G98: po-proposal-papi-v1 | H98: =VLOOKUP(G98,'MuleApps<=>MuleIntegrations'!B:C,2,FALSE) -> MUL-INVENTORYAUTOMATION | I98: =VLOOKUP(G98,'MuleApps<=>MuleIntegrations'!B:D,3,FALSE) -> Mixed
A99: 98 | B99: starkuk-live-workday-papi-v1 | C99: tm1-workday-to-azure-scheduler_tm1-workday-to-azure-scheduler | D99: 0 0 6,7 * * ? * | E99: Enabled | G99: workday-papi-v1 | H99: =VLOOKUP(G99,'MuleApps<=>MuleIntegrations'!B:C,2,FALSE) -> MUL-CONCUR | I99: =VLOOKUP(G99,'MuleApps<=>MuleIntegrations'!B:D,3,FALSE) -> Mixed
A100: 99 | B100: starkuk-live-digitalasset-papi-v1 | C100: cloudinary-to-datalake-stark-azure-delta-load_Trigger for Delta load | D100: 0 0 03 ? * * | E100: Enabled | G100: digitalasset-papi-v1 | H100: =VLOOKUP(G100,'MuleApps<=>MuleIntegrations'!B:C,2,FALSE) -> MUL-DIGITALASSET | I100: =VLOOKUP(G100,'MuleApps<=>MuleIntegrations'!B:D,3,FALSE) -> API
...
